heatzypy/__init__.py
heatzypy/auth.py
heatzypy/const.py
heatzypy/exception.py
heatzypy/heatzy.py
heatzypy/py.typed
heatzypy/websocket.py
heatzypy-2.5.7.dist-info/LICENSE
heatzypy-2.5.7.dist-info/METADATA
heatzypy-2.5.7.dist-info/WHEEL
heatzypy-2.5.7.dist-info/top_level.txt
heatzypy-2.5.7.dist-info/RECORD
