Metadata-Version: 2.2
Name: heatzypy
Version: 2.5.7
Summary: Provides authentication and access to Heatzy module
Author-email: Cyr-ius <cyr-ius@ipocus.net>
License: GPL-3
Project-URL: Homepage, https://github.com/cyr-ius/heatzypy
Keywords: heatzy,websocket,async,climate
Platform: any
Classifier: Programming Language :: Python
Classifier: Development Status :: 5 - Production/Stable
Classifier: License :: OSI Approved :: GNU General Public License v3 or later (GPLv3+)
Classifier: Programming Language :: Python :: 3
Classifier: Programming Language :: Python :: 3.11
Classifier: Programming Language :: Python :: 3.12
Classifier: Programming Language :: Python :: 3.13
Classifier: Framework :: AsyncIO
Classifier: Intended Audience :: Developers
Classifier: Intended Audience :: System Administrators
Classifier: Topic :: Home Automation
Requires-Python: >=3.11.0
License-File: LICENSE
Requires-Dist: aiohttp>=3.8.1
